setup.py
aerolito/__init__.py
aerolito/directives.py
aerolito/exceptions.py
aerolito/kernel.py
aerolito/pattern.py
aerolito/utils.py
aerolito.egg-info/PKG-INFO
aerolito.egg-info/SOURCES.txt
aerolito.egg-info/dependency_links.txt
aerolito.egg-info/requires.txt
aerolito.egg-info/top_level.txt